{
  "$schema": "https://json-schema.org/schema",
  "$id": "OksaiNestLibraryGenerator",
  "title": "NestJS Library Generator",
  "description": "Create a NestJS library with ESM, Vitest, and Biome",
  "cli": "nx",
  "type": "object",
  "examples": [
    {
      "command": "nx g @oksai/nest:nestjs-library --directory=libs/mylib",
      "description": "Generate libs/mylib with ESM"
    }
  ],
  "properties": {
    "directory": {
      "type": "string",
      "description": "A directory where the library is placed.",
      "alias": "dir",
      "$default": {
        "$source": "argv",
        "index": 0
      },
      "x-prompt": "Which directory do you want to create the library in?"
    },
    "name": {
      "type": "string",
      "description": "Library name."
    },
    "buildable": {
      "type": "boolean",
      "description": "Generate a buildable library.",
      "default": false,
      "x-priority": "important"
    },
    "publishable": {
      "type": "boolean",
      "description": "Create a publishable library.",
      "x-priority": "important"
    },
    "importPath": {
      "type": "string",
      "description": "The library name used to import it, like @myorg/my-awesome-lib. Must be a valid npm name."
    },
    "controller": {
      "type": "boolean",
      "description": "Include a controller with the library.",
      "default": false
    },
    "service": {
      "type": "boolean",
      "description": "Include a service with the library.",
      "default": false
    },
    "global": {
      "type": "boolean",
      "description": "Add the Global decorator to the generated module.",
      "default": false
    },
    "bundler": {
      "type": "string",
      "description": "Build bundler to use for buildable/publishable libraries",
      "enum": ["vite", "tsc"],
      "default": "vite",
      "x-prompt": "Which bundler would you like to use? (Vite is recommended for ESM libraries)",
      "x-priority": "important"
    },
    "validation": {
      "type": "string",
      "description": "Validation library for request validation (Standard Schema support)",
      "enum": ["zod", "valibot", "arktype", "class-validator"],
      "default": "zod",
      "x-prompt": "Which validation library would you like to use?",
      "x-priority": "secondary"
    },
    "unitTestRunner": {
      "type": "string",
      "description": "Test runner to use for unit tests.",
      "enum": ["vitest", "none"],
      "default": "vitest",
      "x-prompt": "Which unit test runner would you like to use?",
      "x-priority": "important"
    },
    "tags": {
      "type": "string",
      "description": "Add tags to the library (used for linting).",
      "alias": "t"
    },
    "skipFormat": {
      "type": "boolean",
      "description": "Skip formatting files.",
      "default": false,
      "x-priority": "internal"
    },
    "skipTsConfig": {
      "type": "boolean",
      "description": "Do not update tsconfig.base.json for development experience.",
      "default": false,
      "x-priority": "internal"
    },
    "skipPackageJson": {
      "type": "boolean",
      "description": "Do not add dependencies to package.json.",
      "default": false,
      "x-priority": "internal"
    },
    "strict": {
      "type": "boolean",
      "description": "Whether to enable tsconfig strict mode or not.",
      "default": true
    }
  },
  "additionalProperties": false,
  "required": ["directory"]
}
